{
  "hechos": [
    {
      "fecha": "05-08-2025",
      "entidad": "EVEREST COMPAÑIA DE SEGUROS GENERALES CHILE S.A.",
      "materia": "Cambios en la administración",
      "titulo": "Cambios en la administración",
      "resumen": "EVEREST COMPAÑIA DE SEGUROS GENERALES CHILE S.A. - Cambios en la administración (05-08-2025)",
      "url_pdf": "https://www.cmfchile.cl/sitio/aplic/serdoc/ver_sgd.php?s567=836d59111da9d43eb8f8a683bec6660eVFdwQmVVNVVRVFJOUkZVd1RtcE5NVTVCUFQwPQ==&secuencia=-1&t=1754531161",
      "tiene_pdf": true,
      "relevancia": 5.0,
      "categoria": "MODERADO",
      "es_ipsa": false,
      "link_actualizado": "2025-08-07T01:46:50.923123"
    },
    {
      "fecha": "05-08-2025",
      "entidad": "TANNER SERVICIOS FINANCIEROS S.A.",
      "materia": "Colocación de valores en mercados internacionales y/o nacionales",
      "titulo": "Colocación de valores en mercados internacionales y/o nacionales",
      "resumen": "TANNER SERVICIOS FINANCIEROS S.A. - Colocación de valores en mercados internacionales y/o nacionales (05-08-2025)",
      "url_pdf": "https://www.cmfchile.cl/sitio/aplic/serdoc/ver_sgd.php?s567=b473ed9639c0c3d97fc51334b5f10ebbVFdwQmVVNVVRVFJOUkZVd1RtcE5kMDlSUFQwPQ==&secuencia=-1&t=1754531161",
      "tiene_pdf": true,
      "relevancia": 5.0,
      "categoria": "MODERADO",
      "es_ipsa": false,
      "link_actualizado": "2025-08-07T01:46:50.923146"
    },
    {
      "fecha": "05-08-2025",
      "entidad": "BANCO INTERNACIONAL ADMINISTRADORA GENERAL DE FONDOS S.A.",
      "materia": "Cambios en la administración",
      "titulo": "Cambios en la administración",
      "resumen": "BANCO INTERNACIONAL ADMINISTRADORA GENERAL DE FONDOS S.A. - Cambios en la administración (05-08-2025)",
      "url_pdf": "https://www.cmfchile.cl/sitio/aplic/serdoc/ver_sgd.php?s567=7528b4500d7b0b3ccb39be7beb1aca9cVFdwQmVVNVVRVFJOUkZVd1RtcEZlazVuUFQwPQ==&secuencia=-1&t=1754531161",
      "tiene_pdf": true,
      "relevancia": 5.0,
      "categoria": "MODERADO",
      "es_ipsa": false,
      "link_actualizado": "2025-08-07T01:46:50.923152"
    },
    {
      "fecha": "05-08-2025",
      "entidad": "BANCO RIPLEY",
      "materia": "Otros",
      "titulo": "Otros",
      "resumen": "BANCO RIPLEY - Otros (05-08-2025)",
      "url_pdf": "https://www.cmfchile.cl/sitio/aplic/serdoc/ver_sgd.php?s567=8ff086075d86ae260402cc0b5a062b50VFdwQmVVNVVRVFJOUkZVd1RsUnJlVTFCUFQwPQ==&secuencia=-1&t=1754531161",
      "tiene_pdf": true,
      "relevancia": 5.0,
      "categoria": "MODERADO",
      "es_ipsa": false,
      "link_actualizado": "2025-08-07T01:46:50.923156"
    },
    {
      "fecha": "05-08-2025",
      "entidad": "CEMENTOS BIO BIO S.A.",
      "materia": "Otros",
      "titulo": "Otros",
      "resumen": "CEMENTOS BIO BIO S.A. - Otros (05-08-2025)",
      "url_pdf": "https://www.cmfchile.cl/sitio/aplic/serdoc/ver_sgd.php?s567=c244fb50cda445c5a5a0ba325c16e91dVFdwQmVVNVVRVFJOUkZVd1RsUmpkMDVCUFQwPQ==&secuencia=-1&t=1754531161",
      "tiene_pdf": true,
      "relevancia": 5.0,
      "categoria": "MODERADO",
      "es_ipsa": false,
      "link_actualizado": "2025-08-07T01:46:50.923161"
    },
    {
      "fecha": "05-08-2025",
      "entidad": "CAJA DE COMPENSACION DE ASIGNACION FAMILIAR LOS HEROES",
      "materia": "Colocación de valores en mercados internacionales y/o nacionales",
      "titulo": "Colocación de valores en mercados internacionales y/o nacionales",
      "resumen": "CAJA DE COMPENSACION DE ASIGNACION FAMILIAR LOS HEROES - Colocación de valores en mercados internacionales y/o nacionales (05-08-2025)",
      "url_pdf": "https://www.cmfchile.cl/sitio/aplic/serdoc/ver_sgd.php?s567=9450f22b042ecef30e7d24769079fc2dVFdwQmVVNVVRVFJOUkZVd1RsUlpNMDEzUFQwPQ==&secuencia=-1&t=1754531161",
      "tiene_pdf": true,
      "relevancia": 5.0,
      "categoria": "MODERADO",
      "es_ipsa": false,
      "link_actualizado": "2025-08-07T01:46:50.923166"
    },
    {
      "fecha": "05-08-2025",
      "entidad": "AVANTE RENTA V FONDO DE INVERSION",
      "materia": "Otros",
      "titulo": "Otros",
      "resumen": "AVANTE RENTA V FONDO DE INVERSION - Otros (05-08-2025)",
      "url_pdf": "https://www.cmfchile.cl/sitio/aplic/serdoc/ver_sgd.php?s567=50939490eb5f53a9ac0f0d930d246e28VFdwQmVVNVVRVFJOUkZVd1RrUnJORTFuUFQwPQ==&secuencia=-1&t=1754531161",
      "tiene_pdf": true,
      "relevancia": 5.0,
      "categoria": "MODERADO",
      "es_ipsa": false,
      "link_actualizado": "2025-08-07T01:46:50.923171"
    },
    {
      "fecha": "05-08-2025",
      "entidad": "CAJA DE COMPENSACION DE ASIGNACION FAMILIAR DE LOS ANDES",
      "materia": "Cambio de representante legal",
      "titulo": "Cambio de representante legal",
      "resumen": "CAJA DE COMPENSACION DE ASIGNACION FAMILIAR DE LOS ANDES - Cambio de representante legal (05-08-2025)",
      "url_pdf": "https://www.cmfchile.cl/sitio/aplic/serdoc/ver_sgd.php?s567=3521f3b5d03f73abe47433a2f7cf3596VFdwQmVVNVVRVFJOUkZVd1RrUkZNazFuUFQwPQ==&secuencia=-1&t=1754531161",
      "tiene_pdf": true,
      "relevancia": 5.0,
      "categoria": "MODERADO",
      "es_ipsa": false,
      "link_actualizado": "2025-08-07T01:46:50.923177"
    }
  ]
}